Metadata-Version: 2.1
Name: InfiniteTrends
Version: 0.3
Summary: An upgraded Google Trends API that can query infinitely many terms.
Home-page: https://www.ashernoel.io
Author: Asher Noel
Author-email: asher13a@gmail.com
License: MIT
Download-URL: https://github.com/ashernoel/InfiniteTrends/archive/v_03.tar.gz
Keywords: Google Trends,Interest,Viral,Related
Platform: UNKNOWN
Classifier: Development Status :: 3 - Alpha
Classifier: Intended Audience :: Developers
Classifier: Topic :: Software Development :: Build Tools
Classifier: License :: OSI Approved :: MIT License
